imdabessay/__init__.py
imdabessay/__main__.py
mksmith/__init__.py
mksmith/__main__.py
mksmith/feed.py
mksmith/viewer.py
reader/__init__.py
reader/__main__.py
reader/config.cfg
reader/feed.py
reader/viewer.py
imdabessay-1.0.3.dist-info/LICENSE
imdabessay-1.0.3.dist-info/METADATA
imdabessay-1.0.3.dist-info/WHEEL
imdabessay-1.0.3.dist-info/entry_points.txt
imdabessay-1.0.3.dist-info/top_level.txt
imdabessay-1.0.3.dist-info/RECORD
